illex/__init__.py
illex/__main__.py
illex/builtins/__init__.py
illex/builtins/collections/list.py
illex/builtins/collections/options.py
illex/builtins/date/date.py
illex/builtins/math/abs.py
illex/builtins/math/calc.py
illex/builtins/math/ceil.py
illex/builtins/math/fabs.py
illex/builtins/math/float.py
illex/builtins/math/floor.py
illex/builtins/math/int.py
illex/builtins/networks/cidr.py
illex/builtins/networks/is_public.py
illex/builtins/networks/resolve.py
illex/builtins/security/decrypt.py
illex/builtins/security/encrypt.py
illex/builtins/security/gen_password.py
illex/builtins/security/hash.py
illex/builtins/strings/capitalize.py
illex/builtins/strings/lowercase.py
illex/builtins/strings/replace.py
illex/builtins/strings/split.py
illex/builtins/strings/trim.py
illex/builtins/strings/uppercase.py
illex/builtins/utils/if.py
illex/builtins/utils/include.py
illex/builtins/utils/rand.py
illex/builtins/utils/repeat.py
illex/core/registry.py
illex/core/safe_eval.py
illex/core/safe_globals.py
illex/core/variables.py
illex/decorators/__init__.py
illex/decorators/function.py
illex/decorators/math.py
illex/decorators/multi_param.py
illex/decorators/network.py
illex/parser/__init__.py
illex/parser/parse.py
illex/parser/helpers/__init__.py
illex/parser/helpers/evalv.py
illex/parser/helpers/extract_bracket_content.py
illex/parser/helpers/extract_value_until_delimiter.py
illex/parser/helpers/is_comment_line.py
illex/parser/helpers/process_bracket_access.py
illex/parser/helpers/process_handler_call.py
illex/parser/helpers/process_variable_assignment.py
illex/parser/helpers/process_variable_reference.py
illex/parser/steps/__init__.py
illex/parser/steps/step0.py
illex/parser/steps/step1.py
illex/parser/steps/step2.py
illex/parser/steps/step3.py
illex-0.1.4.dist-info/METADATA
illex-0.1.4.dist-info/WHEEL
illex-0.1.4.dist-info/entry_points.txt
illex-0.1.4.dist-info/top_level.txt
illex-0.1.4.dist-info/RECORD
