Metadata-Version: 2.4
Name: illex
Version: 0.1.4
Summary: Inline Language for Logic and EXpressions
Author-email: Gustavo Zeloni <gustavo@gzeloni.dev>
License: GNU General Public License v3.0
Project-URL: Homepage, https://github.com/gzeloni/illex
Project-URL: Documentation, https://docs.illex.dev
Project-URL: Bug Tracker, https://github.com/gzeloni/illex/issues
Requires-Python: >=3.8
Requires-Dist: pytz>=2023.3
Requires-Dist: sympy==1.13.3
Requires-Dist: cryptography==44.0.2
